MANIFEST.in
README.rst
setup.cfg
setup.py
requery/__init__.py
requery/admin.py
requery/forms.py
requery/local_settings.py
requery/models.py
requery/tests.py
requery/views.py
requery.egg-info/PKG-INFO
requery.egg-info/SOURCES.txt
requery.egg-info/dependency_links.txt
requery.egg-info/not-zip-safe
requery.egg-info/requires.txt
requery.egg-info/top_level.txt
requery/static/MultiLevelPushMenu/css/component.css
requery/static/MultiLevelPushMenu/css/demo.css
requery/static/MultiLevelPushMenu/css/icons.css
requery/static/MultiLevelPushMenu/css/normalize.css
requery/static/MultiLevelPushMenu/fonts/codropsicons/codropsicons.eot
requery/static/MultiLevelPushMenu/fonts/codropsicons/codropsicons.svg
requery/static/MultiLevelPushMenu/fonts/codropsicons/codropsicons.ttf
requery/static/MultiLevelPushMenu/fonts/codropsicons/codropsicons.woff
requery/static/MultiLevelPushMenu/fonts/codropsicons/license.txt
requery/static/MultiLevelPushMenu/fonts/linecons/Read Me.txt
requery/static/MultiLevelPushMenu/fonts/linecons/license.txt
requery/static/MultiLevelPushMenu/fonts/linecons/linecons.dev.svg
requery/static/MultiLevelPushMenu/fonts/linecons/linecons.eot
requery/static/MultiLevelPushMenu/fonts/linecons/linecons.svg
requery/static/MultiLevelPushMenu/fonts/linecons/linecons.ttf
requery/static/MultiLevelPushMenu/fonts/linecons/linecons.woff
requery/static/MultiLevelPushMenu/fonts/linecons/lte-ie7.js
requery/static/MultiLevelPushMenu/js/classie.js
requery/static/MultiLevelPushMenu/js/mlpushmenu.js
requery/static/MultiLevelPushMenu/js/modernizr.custom.js
requery/static/css/bootstrap.min.css
requery/static/css/font-awesome.min.css
requery/static/css/requery.css
requery/static/font-awesome-4.3.0/css/font-awesome.css
requery/static/font-awesome-4.3.0/css/font-awesome.min.css
requery/static/font-awesome-4.3.0/fonts/FontAwesome.otf
requery/static/font-awesome-4.3.0/fonts/fontawesome-webfont.eot
requery/static/font-awesome-4.3.0/fonts/fontawesome-webfont.svg
requery/static/font-awesome-4.3.0/fonts/fontawesome-webfont.ttf
requery/static/font-awesome-4.3.0/fonts/fontawesome-webfont.woff
requery/static/font-awesome-4.3.0/fonts/fontawesome-webfont.woff2
