Metadata-Version: 1.1
Name: requery
Version: 0.4.0.0
Summary: Simple way to store and use queries in database for use of DBA for Django Admin
Home-page: http://github.com/ebertti/requery/
Author: Ezequiel Bertti
Author-email: ebertti@gmail.com
License: MIT License
Keywords: query dba repository report django
Platform: OS Independent
Classifier: Development Status :: 4 - Beta
Classifier: Framework :: Django
Classifier: Intended Audience :: Developers
Classifier: License :: OSI Approved :: MIT License
Classifier: Natural Language :: English
Classifier: Natural Language :: Portuguese (Brazilian)
Classifier: Operating System :: OS Independent
Classifier: Programming Language :: Python :: 2
Classifier: Programming Language :: Python :: 2.7
Classifier: Programming Language :: Python :: 3
Classifier: Programming Language :: Python :: 3.4
Classifier: Topic :: Database
Classifier: Topic :: Database :: Front-Ends
